addnumbersapp/__init__.py
addnumbersapp/app.py
addnumbersapp/templates/index.html
AddNumbersApp-0.1.7.dist-info/METADATA
AddNumbersApp-0.1.7.dist-info/WHEEL
AddNumbersApp-0.1.7.dist-info/entry_points.txt
AddNumbersApp-0.1.7.dist-info/top_level.txt
AddNumbersApp-0.1.7.dist-info/RECORD
