Metadata-Version: 2.1
Name: AddNumbersApp
Version: 0.1.7
Requires-Dist: Flask
